LICENSE.md
MANIFEST.in
README.rst
requirements.txt
setup.py
lyrid/__init__.py
lyrid/_actor_system.py
lyrid/py.typed
lyrid.egg-info/PKG-INFO
lyrid.egg-info/SOURCES.txt
lyrid.egg-info/dependency_links.txt
lyrid.egg-info/not-zip-safe
lyrid.egg-info/top_level.txt
lyrid/api/__init__.py
lyrid/api/actor/__init__.py
lyrid/api/actor/switch/__init__.py
lyrid/api/actor/switch/decorator.py
lyrid/api/actor/switch/handle_rule.py
lyrid/api/actor/switch/property_injection.py
lyrid/api/actor/switch/switch.py
lyrid/api/actor/switch/use_switch.py
lyrid/api/actor/switch/handle_policy/__init__.py
lyrid/api/actor/switch/handle_policy/ask_message_type.py
lyrid/api/actor/switch/handle_policy/background_task_exited.py
lyrid/api/actor/switch/handle_policy/child_spawned.py
lyrid/api/actor/switch/handle_policy/child_stopped.py
lyrid/api/actor/switch/handle_policy/error_message.py
lyrid/api/actor/switch/handle_policy/message_type.py
lyrid/base/__init__.py
lyrid/base/command_processing_loop.py
lyrid/base/node.py
lyrid/base/scheduler.py
lyrid/base/actor/__init__.py
lyrid/base/actor/_abstract.py
lyrid/base/actor/_actor.py
lyrid/base/actor/_process.py
lyrid/base/actor/_status.py
lyrid/base/background_task_executor/__init__.py
lyrid/base/background_task_executor/_thread.py
lyrid/base/background_task_executor/_threading_client.py
lyrid/base/messenger/__init__.py
lyrid/base/messenger/_command_processor.py
lyrid/base/messenger/_messenger.py
lyrid/base/system/__init__.py
lyrid/base/system/_root.py
lyrid/base/system/_system.py
lyrid/base/system/_task.py
lyrid/base/system/placement/__init__.py
lyrid/base/system/placement/_matcher.py
lyrid/base/system/placement/_policy.py
lyrid/common/__init__.py
lyrid/common/_id_generator.py
lyrid/common/_randomizer.py
lyrid/common/_threading_client.py
lyrid/core/__init__.py
lyrid/core/background_task/__init__.py
lyrid/core/background_task/_executor.py
lyrid/core/background_task/_message.py
lyrid/core/command_processing_loop/__init__.py
lyrid/core/command_processing_loop/_command.py
lyrid/core/command_processing_loop/_processor.py
lyrid/core/common/__init__.py
lyrid/core/common/_id_generator.py
